configstore/__init__.py
configstore/utils.py
dbs/__init__.py
dbs/auth.py
dbs/ewf.py
dbs/image_description.py
dbs/team.py
dbs/text_classification.py
dbscli/__init__.py
dbscli/ask.py
dbscli/ewf.py
dbscli/main.py
dbscli/utils.py
dbscli/validators.py
dbs_cli-0.0.3.dist-info/METADATA
dbs_cli-0.0.3.dist-info/WHEEL
dbs_cli-0.0.3.dist-info/entry_points.txt
dbs_cli-0.0.3.dist-info/top_level.txt
dbs_cli-0.0.3.dist-info/RECORD
